{
  "supplier": "Eton House Residential Home",
  "legal_name_searched": "Eton House Residential Home",
  "ch_found": true,
  "ch_name": "ETON RESIDENTIAL LIMITED",
  "company_number": "08020244",
  "match_confidence": "medium",
  "ch_status": "active",
  "is_suspicious_status": false,
  "date_of_cessation": null,
  "incorporated": "2012-04-04",
  "company_type": "ltd",
  "registered_address": "C/O Lismoyne Hotel, 45 Church Road, Fleet, GU51 4NE",
  "sic_codes": [
    "68209"
  ],
  "sic_description": "68209",
  "accounts_overdue": false,
  "is_council_controlled": false,
  "psc_names": [
    "Eton Developments Limited"
  ],
  "director_names": [
    "RADIA, Dev Ramesh"
  ],
  "director_count": 1
}